Metadata-Version: 2.1
Name: fslog
Version: 0.1.3
Summary: Customizable log formatter that supports recursive log sections
Home-page: http://github.com/fsossai/fslog
Author: Federico Sossai
Author-email: federico.sossai@gmail.com
